postal/token_types.pyi
postal/_parser.cpython-310-darwin.so
postal/pytokenize.c
postal/normalize.pyi
postal/pytokentypes.c
postal/pydedupe.c
postal/__init__.pyi
postal/token_types.py
postal/_near_dupe.cpython-310-darwin.so
postal/_tokenize.cpython-310-darwin.so
postal/dedupe.py
postal/normalize.py
postal/tokenize.pyi
postal/__init__.py
postal/dedupe.pyi
postal/pyutils.c
postal/parser.py
postal/parser.pyi
postal/pyparser.c
postal/_dedupe.cpython-310-darwin.so
postal/expand.pyi
postal/_token_types.cpython-310-darwin.so
postal/near_dupe.py
postal/pyexpand.c
postal/_expand.cpython-310-darwin.so
postal/py.typed
postal/near_dupe.pyi
postal/_normalize.cpython-310-darwin.so
postal/pyneardupe.c
postal/pynormalize.c
postal/tokenize.py
postal/pyutils.h
postal/expand.py
postal/tests/test_parser.py
postal/tests/__init__.py
postal/tests/test_expand.py
postal/utils/encoding.py
postal/utils/__init__.pyi
postal/utils/__init__.py
postal/utils/enum.py
postal/utils/encoding.pyi
postal/utils/enum.pyi
postal/.dylibs/libpostal.1.dylib
pypostal_multiarch-1.0.3.dist-info/RECORD
pypostal_multiarch-1.0.3.dist-info/WHEEL
pypostal_multiarch-1.0.3.dist-info/top_level.txt
pypostal_multiarch-1.0.3.dist-info/METADATA
pypostal_multiarch-1.0.3.dist-info/licenses/LICENSE
